transphone/__init__.py
transphone/config.py
transphone/g2p.py
transphone/run.py
transphone/tokenizer.py
transphone/utils.py
transphone/bin/__init__.py
transphone/bin/download_model.py
transphone/bin/eval_epitran.py
transphone/bin/eval_g2p.py
transphone/bin/eval_zsl_g2p.py
transphone/bin/g2p.py
transphone/bin/tokenize.py
transphone/bin/train_g2p.py
transphone/bin/update_model.py
transphone/data/__init__.py
transphone/data/dataset.py
transphone/data/grapheme.py
transphone/data/loader.py
transphone/data/utils.py
transphone/data/vocab.py
transphone/data/exp/042801_base.yml
transphone/data/exp/__init__.py
transphone/lang/__init__.py
transphone/lang/base_tokenizer.py
transphone/lang/epitran_tokenizer.py
transphone/lang/g2p_tokenizer.py
transphone/lang/cmn/__init__.py
transphone/lang/cmn/normalizer.py
transphone/lang/cmn/tokenizer.py
transphone/lang/eng/__init__.py
transphone/lang/eng/normalizer.py
transphone/lang/eng/tokenizer.py
transphone/lang/jpn/__init__.py
transphone/lang/jpn/conv_table.py
transphone/lang/jpn/jaconv.py
transphone/lang/jpn/kana2phoneme.py
transphone/lang/jpn/normalizer.py
transphone/lang/jpn/tokenizer.py
transphone/model/__init__.py
transphone/model/checkpoint_utils.py
transphone/model/dataset.py
transphone/model/ensemble.py
transphone/model/grapheme.py
transphone/model/loader.py
transphone/model/lstm.py
transphone/model/transformer.py
transphone/model/utils.py
transphone/model/vocab.py
transphone/pretrained/__init__.py
transphone-1.5.3.dist-info/LICENSE
transphone-1.5.3.dist-info/METADATA
transphone-1.5.3.dist-info/WHEEL
transphone-1.5.3.dist-info/top_level.txt
transphone-1.5.3.dist-info/RECORD
