Metadata-Version: 2.1
Name: transphone
Version: 1.5.3
Summary: a multilingual g2p/p2g model
Home-page: https://github.com/xinjli/transphone
Author: Xinjian Li
Author-email: xinjianl@cs.cmu.edu
License: UNKNOWN
Platform: UNKNOWN
License-File: LICENSE
Requires-Dist: scipy
Requires-Dist: numpy
Requires-Dist: panphon
Requires-Dist: torch
Requires-Dist: editdistance
Requires-Dist: requests
Requires-Dist: tqdm
Requires-Dist: pyyaml
Requires-Dist: phonepiece
Requires-Dist: epitran
Requires-Dist: unidecode
Requires-Dist: mecab-python3
Requires-Dist: cmudict
